eurlex/__init__.py
eurlex/eurlex.py
pyeurlex-0.2.9.dist-info/LICENSE
pyeurlex-0.2.9.dist-info/WHEEL
pyeurlex-0.2.9.dist-info/METADATA
pyeurlex-0.2.9.dist-info/RECORD
