Metadata-Version: 2.1
Name: pyeurlex
Version: 0.2.9
Summary: This is a python module to create SPARQL queries for the EU Cellar repository, run them and subsequently download their data. Notably, it directly supports all resource types.
Author: step21
Author-email: step21@devtal.de
Requires-Python: >=3.7.2,<4.0.0
Classifier: Programming Language :: Python :: 3
Classifier: Programming Language :: Python :: 3.8
Classifier: Programming Language :: Python :: 3.9
Classifier: Programming Language :: Python :: 3.10
Requires-Dist: beautifulsoup4 (>=4.11.1,<5.0.0)
Requires-Dist: fire (>=0.4.0,<0.5.0)
Requires-Dist: halo (>=0.0.31,<0.0.32)
Requires-Dist: lxml (>=4.9.1,<5.0.0)
Requires-Dist: pandas (>=1.3.0,<2.0.0)
Requires-Dist: pdfminer.six (>=20220524,<20220525)
Requires-Dist: requests (>=2.28.1,<3.0.0)
Requires-Dist: scriv[toml] (>=0.16.0,<0.17.0)
Requires-Dist: sparql-dataframe (>=0.4,<0.5)
Requires-Dist: typing-extensions (>=4.3.0,<5.0.0); python_full_version >= "3.7.0" and python_full_version < "3.8.0"
